alfasim_sdk/__init__.py
alfasim_sdk/default_tasks.py
alfasim_sdk/_internal/__init__.py
alfasim_sdk/_internal/alfasim_sdk_utils.py
alfasim_sdk/_internal/cli.py
alfasim_sdk/_internal/constants.py
alfasim_sdk/_internal/context.py
alfasim_sdk/_internal/hook_specs.py
alfasim_sdk/_internal/hook_specs_gui.py
alfasim_sdk/_internal/layout.py
alfasim_sdk/_internal/models.py
alfasim_sdk/_internal/status.py
alfasim_sdk/_internal/types.py
alfasim_sdk/_internal/units.py
alfasim_sdk/_internal/validators.py
alfasim_sdk/_internal/variables.py
alfasim_sdk/_internal/version.py
alfasim_sdk/_internal/alfacase/__init__.py
alfasim_sdk/_internal/alfacase/alfacase.py
alfasim_sdk/_internal/alfacase/alfacase_to_case.py
alfasim_sdk/_internal/alfacase/alfatable.py
alfasim_sdk/_internal/alfacase/case_description.py
alfasim_sdk/_internal/alfacase/case_description_attributes.py
alfasim_sdk/_internal/alfacase/case_to_alfacase.py
alfasim_sdk/_internal/alfacase/generate_case_description_docstring.py
alfasim_sdk/_internal/alfacase/generate_schema.py
alfasim_sdk/_internal/alfacase/plugin_alfacase_to_case.py
alfasim_sdk/_internal/alfacase/plugin_introspection.py
alfasim_sdk/_internal/alfacase/schema.py
alfasim_sdk/alfasim_sdk_api/alfasim_sdk.h
alfasim_sdk/alfasim_sdk_api/api.h
alfasim_sdk/alfasim_sdk_api/common.h
alfasim_sdk/alfasim_sdk_api/detail/api_pointers.h
alfasim_sdk/alfasim_sdk_api/detail/bootstrap_linux.h
alfasim_sdk/alfasim_sdk_api/detail/bootstrap_win.h
alfasim_sdk/result_reader/__init__.py
alfasim_sdk/result_reader/aggregator.py
alfasim_sdk/result_reader/aggregator_constants.py
alfasim_sdk/result_reader/reader.py
alfasim_sdk/testing/__init__.py
alfasim_sdk/testing/fixtures.py
alfasim_sdk_plugins/__init__.py
alfasim_sdk-2024.2.dist-info/LICENSE
alfasim_sdk-2024.2.dist-info/METADATA
alfasim_sdk-2024.2.dist-info/WHEEL
alfasim_sdk-2024.2.dist-info/entry_points.txt
alfasim_sdk-2024.2.dist-info/top_level.txt
alfasim_sdk-2024.2.dist-info/RECORD
