Metadata-Version: 2.1
Name: alfasim_sdk
Version: 2024.2
Summary: ALFAsim API/SDK
Home-page: https://github.com/esss/alfasim-sdk
Author: ESSS
Author-email: foss@esss.co
Classifier: Intended Audience :: Developers
Classifier: License :: OSI Approved :: MIT License
Classifier: Natural Language :: English
Classifier: Programming Language :: Python :: 3.8
Classifier: Programming Language :: Python :: 3.9
Classifier: Programming Language :: Python :: 3.10
Requires-Python: >=3.8
License-File: LICENSE
Requires-Dist: python-hookman
Requires-Dist: typing-inspect
Requires-Dist: strictyaml>=1.4.3
Requires-Dist: boltons
Requires-Dist: Click>=7.0
Requires-Dist: barril<2.0,>=1.13
Requires-Dist: pluggy>=0.13.0
Requires-Dist: h5py
